atai_image_tool/__init__.py
atai_image_tool/cli.py
atai_image_tool/core.py
atai_image_tool-0.0.2.dist-info/LICENSE
atai_image_tool-0.0.2.dist-info/METADATA
atai_image_tool-0.0.2.dist-info/WHEEL
atai_image_tool-0.0.2.dist-info/entry_points.txt
atai_image_tool-0.0.2.dist-info/top_level.txt
atai_image_tool-0.0.2.dist-info/RECORD
