Metadata-Version: 2.2
Name: atai-image-tool
Version: 0.0.2
Summary: Extract text from images using OCR and save to JSON or print to console
Home-page: https://github.com/AtomGradient/atai-image-tool
Author: AtomGradient
Author-email: AtomGradient <alex@atomgradient.com>
License: MIT
Project-URL: Homepage, https://github.com/AtomGradient/atai-image-tool
Project-URL: Bug Tracker, https://github.com/AtomGradient/atai-image-tool/issues
Keywords: ocr,image,text,extraction,ai
Classifier: Programming Language :: Python :: 3
Classifier: License :: OSI Approved :: MIT License
Classifier: Operating System :: OS Independent
Requires-Python: >=3.6
License-File: LICENSE
Requires-Dist: easyocr
Dynamic: author
Dynamic: home-page
Dynamic: requires-python
